kubeflow-minerva/__init__.py
kubeflow-minerva/_nbdev.py
kubeflow-minerva/database.py
minerva/__init__.py
minerva/_nbdev.py
minerva/database.py
kubeflow_minerva-0.0.3.dist-info/LICENSE
kubeflow_minerva-0.0.3.dist-info/METADATA
kubeflow_minerva-0.0.3.dist-info/WHEEL
kubeflow_minerva-0.0.3.dist-info/entry_points.txt
kubeflow_minerva-0.0.3.dist-info/top_level.txt
kubeflow_minerva-0.0.3.dist-info/RECORD
