Metadata-Version: 2.1
Name: kubeflow-minerva
Version: 0.0.3
Summary: A meta-learning platform for ML
Home-page: https://github.com/kandrio/minerva/tree/master/
Author: Konstantinos Andriopoulos
Author-email: kandrio@arrikto.com
License: Apache Software License 2.0
Keywords: ML,meta-learning,supervised,platform,machine-learning
Platform: UNKNOWN
Classifier: Development Status :: 3 - Alpha
Classifier: Intended Audience :: Developers
Classifier: License :: OSI Approved :: Apache Software License
Classifier: Natural Language :: English
Classifier: Programming Language :: Python :: 3.6
Classifier: Programming Language :: Python :: 3.7
Classifier: Programming Language :: Python :: 3.8
Requires-Python: >=3.6
Requires-Dist: pymongo
